secret_run/__init__.py
secret_run/cli/__init__.py
secret_run/cli/main.py
secret_run/cli/commands/__init__.py
secret_run/cli/commands/audit.py
secret_run/cli/commands/cloud.py
secret_run/cli/commands/config.py
secret_run/cli/commands/rotate.py
secret_run/cli/commands/run.py
secret_run/cli/commands/validate.py
secret_run/core/__init__.py
secret_run/core/cloud_integrations.py
secret_run/core/executor.py
secret_run/core/loaders.py
secret_run/core/rotation.py
secret_run/core/secrets.py
secret_run/core/security.py
secret_run/core/validators.py
secret_run/utils/__init__.py
secret_run/utils/config.py
secret_run/utils/logging.py
secret_run/utils/platform.py
secret_run-0.1.0.dist-info/METADATA
secret_run-0.1.0.dist-info/WHEEL
secret_run-0.1.0.dist-info/entry_points.txt
secret_run-0.1.0.dist-info/licenses/LICENSE
secret_run-0.1.0.dist-info/RECORD
