Metadata-Version: 2.4
Name: secret-run
Version: 0.1.0
Summary: Secure command execution with temporary secret injection
Project-URL: Homepage, https://github.com/Sherin-SEF-AI/secret-run
Project-URL: Documentation, https://github.com/Sherin-SEF-AI/secret-run#readme
Project-URL: Repository, https://github.com/Sherin-SEF-AI/secret-run.git
Project-URL: Issues, https://github.com/Sherin-SEF-AI/secret-run/issues
Project-URL: Changelog, https://github.com/Sherin-SEF-AI/secret-run/blob/master/CHANGELOG.md
Author-email: sherin joseph roy <sherin.joseph2217@gmail.com>
License: MIT
License-File: LICENSE
Keywords: cli,devops,environment,secrets,security
Classifier: Development Status :: 5 - Production/Stable
Classifier: Environment :: Console
Classifier: Intended Audience :: Developers
Classifier: License :: OSI Approved :: MIT License
Classifier: Operating System :: OS Independent
Classifier: Programming Language :: Python :: 3
Classifier: Programming Language :: Python :: 3.10
Classifier: Programming Language :: Python :: 3.11
Classifier: Programming Language :: Python :: 3.12
Classifier: Topic :: Security
Classifier: Topic :: Software Development :: Libraries :: Python Modules
Classifier: Topic :: System :: Systems Administration
Requires-Python: >=3.10
Requires-Dist: aiofiles>=23.0.0
Requires-Dist: click>=8.0.0
Requires-Dist: cryptography>=41.0.0
Requires-Dist: keyring>=24.0.0
Requires-Dist: platformdirs>=3.0.0
Requires-Dist: psutil>=5.9.0
Requires-Dist: pydantic>=2.0.0
Requires-Dist: pyperclip>=1.8.0
Requires-Dist: python-dotenv>=1.0.0
Requires-Dist: pyyaml>=6.0.0
Requires-Dist: rich>=13.0.0
Requires-Dist: typer[all]>=0.9.0
Provides-Extra: all
Requires-Dist: azure-keyvault-secrets>=4.7.0; extra == 'all'
Requires-Dist: boto3>=1.28.0; extra == 'all'
Requires-Dist: google-cloud-secret-manager>=2.16.0; extra == 'all'
Requires-Dist: hvac>=1.2.0; extra == 'all'
Requires-Dist: requests>=2.31.0; extra == 'all'
Requires-Dist: textual>=0.38.0; extra == 'all'
Requires-Dist: watchdog>=3.0.0; extra == 'all'
Provides-Extra: aws
Requires-Dist: boto3>=1.28.0; extra == 'aws'
Provides-Extra: azure
Requires-Dist: azure-keyvault-secrets>=4.7.0; extra == 'azure'
Provides-Extra: dev
Requires-Dist: black>=23.7.0; extra == 'dev'
Requires-Dist: mypy>=1.5.0; extra == 'dev'
Requires-Dist: pre-commit>=3.3.0; extra == 'dev'
Requires-Dist: pytest-asyncio>=0.21.0; extra == 'dev'
Requires-Dist: pytest-cov>=4.1.0; extra == 'dev'
Requires-Dist: pytest-mock>=3.11.0; extra == 'dev'
Requires-Dist: pytest>=7.4.0; extra == 'dev'
Requires-Dist: ruff>=0.0.284; extra == 'dev'
Provides-Extra: gcp
Requires-Dist: google-cloud-secret-manager>=2.16.0; extra == 'gcp'
Provides-Extra: tui
Requires-Dist: textual>=0.38.0; extra == 'tui'
Provides-Extra: vault
Requires-Dist: hvac>=1.2.0; extra == 'vault'
